django_easyjwt-0.7.5.dist-info/licenses/LICENCE
easyjwt_auth/__init__.py
easyjwt_auth/apps.py
easyjwt_auth/authentication.py
easyjwt_auth/backends.py
easyjwt_auth/exceptions.py
easyjwt_auth/models.py
easyjwt_auth/py.typed
easyjwt_auth/serializers.py
easyjwt_auth/settings.py
easyjwt_auth/state.py
easyjwt_auth/tokens.py
easyjwt_auth/urls.py
easyjwt_auth/utils.py
easyjwt_auth/views.py
easyjwt_auth/token_blacklist/__init__.py
easyjwt_auth/token_blacklist/admin.py
easyjwt_auth/token_blacklist/apps.py
easyjwt_auth/token_blacklist/models.py
easyjwt_auth/token_blacklist/management/__init__.py
easyjwt_auth/token_blacklist/management/commands/__init__.py
easyjwt_auth/token_blacklist/management/commands/flushexpiredtokens.py
easyjwt_client/__init__.py
easyjwt_client/apps.py
easyjwt_client/authentication.py
easyjwt_client/serializers.py
easyjwt_client/settings.py
easyjwt_client/tests.py
easyjwt_client/urls.py
easyjwt_client/utils.py
easyjwt_client/views.py
easyjwt_user/__init__.py
easyjwt_user/admin.py
easyjwt_user/apps.py
easyjwt_user/models.py
easyjwt_user/serializers.py
easyjwt_user/settings.py
easyjwt_user/tests.py
easyjwt_user/urls.py
easyjwt_user/views.py
easyjwt_user/migrations/0001_initial.py
easyjwt_user/migrations/__init__.py
django_easyjwt-0.7.5.dist-info/METADATA
django_easyjwt-0.7.5.dist-info/WHEEL
django_easyjwt-0.7.5.dist-info/top_level.txt
django_easyjwt-0.7.5.dist-info/RECORD
