Metadata-Version: 2.4
Name: django-easyjwt
Version: 0.7.5
Summary: A convenient package for building both client and server implementations for JWTs or Json Web Tokens. It allows you to build either side by only including the module you need and includes an optional custom user model.
Home-page: https://github.com/garrethcain/django-easyjwt
Author: Garreth Cain
Author-email: garrethccain@gmail.com
License: MIT
Classifier: Environment :: Web Environment
Classifier: Framework :: Django
Classifier: Framework :: Django :: 3.2
Classifier: Intended Audience :: Developers
Classifier: License :: OSI Approved :: BSD License
Classifier: Operating System :: OS Independent
Classifier: Programming Language :: Python
Classifier: Programming Language :: Python :: 3
Classifier: Programming Language :: Python :: 3 :: Only
Classifier: Programming Language :: Python :: 3.6
Classifier: Programming Language :: Python :: 3.7
Classifier: Programming Language :: Python :: 3.8
Classifier: Programming Language :: Python :: 3.9
Classifier: Programming Language :: Python :: 3.10
Classifier: Programming Language :: Python :: 3.11
Classifier: Programming Language :: Python :: 3.12
Classifier: Programming Language :: Python :: 3.13
Classifier: Topic :: Internet :: WWW/HTTP
Classifier: Topic :: Internet :: WWW/HTTP
Classifier: Topic :: Internet :: WWW/HTTP :: Dynamic Content
Requires-Python: >=3.8
License-File: LICENCE
Requires-Dist: Django>=3.2
Requires-Dist: djangorestframework>=3.12.4
Requires-Dist: requests>=2.24.0
Requires-Dist: PyJWT>=2.8.0
Dynamic: license-file
